pylacus/__init__.py
pylacus/api.py
pylacus/py.typed
pylacus-1.21.2.dist-info/METADATA
pylacus-1.21.2.dist-info/WHEEL
pylacus-1.21.2.dist-info/entry_points.txt
pylacus-1.21.2.dist-info/licenses/LICENSE
pylacus-1.21.2.dist-info/RECORD
